djangomosquito/__init__.py
djangomosquito/middleware.py
djangomosquito-0.0.4.dist-info/LICENSE
djangomosquito-0.0.4.dist-info/METADATA
djangomosquito-0.0.4.dist-info/WHEEL
djangomosquito-0.0.4.dist-info/top_level.txt
djangomosquito-0.0.4.dist-info/RECORD
