Metadata-Version: 2.1
Name: djangomosquito
Version: 0.0.4
Summary: Limit visitors to your django app by count
Home-page: https://github.com/E-RROR/django-mosquito/
Author: Sina Farhadi
Author-email: sina.farhadi.cyber@gmail.com
License: MIT
Keywords: django,visit,filter,limit,mosquito,django mosquito
Platform: UNKNOWN
Classifier: Framework :: Django
